{
  "profile": "Profil",
  "username": "Nom d'utilisateur",
  "played": "Parties jouées",
  "wins": "Victoires",
  "joined": "Inscrit",
  "add_friend": "Ajouter un ami",
  "block_user": "Bloquer l'utilisateur",
  "friend_added": "Ami ajouté !",
  "user_blocked": "Utilisateur bloqué !",
  "error": "Erreur",
  "loading": "Chargement...",
  "fetch_error": "Échec de la récupération des données utilisateur",
  "login_error": "Veuillez vous connecter pour voir votre profil",
  "play_ai": "Jouer contre l'IA",
  "play_user": "Jouer contre un utilisateur",
  "settings": "Paramètres",
  "account_settings": "Paramètres du compte",
  "profile_picture": "Photo de profil",
  "change_nickname": "Changer le pseudo",
  "enter_new_nickname": "Entrez un nouveau pseudo",
  "save_nickname": "Enregistrer le pseudo",
  "change_password": "Changer le mot de passe",
  "enter_new_password": "Entrez un nouveau mot de passe",
  "save_password": "Enregistrer le mot de passe",
  "cancel": "Annuler",
  "image_size_error": "La taille de l'image doit être inférieure à 5 Mo",
  "invalid_image_error": "Veuillez sélectionner un fichier image valide",
  "unauthorized_error": "Non autorisé",
  "profile_picture_updated": "Photo de profil mise à jour avec succès",
  "failed_update_picture": "Échec de la mise à jour de la photo de profil",
  "empty_password_error": "Le mot de passe ne peut pas être vide",
  "password_updated": "Mot de passe mis à jour avec succès",
  "failed_update_password": "Échec de la mise à jour du mot de passe",
  "empty_nickname_error": "Le pseudo ne peut pas être vide",
  "nickname_unchanged": "Le pseudo n'a pas changé",
  "nickname_updated": "Pseudo mis à jour avec succès",
  "failed_update_nickname": "Échec de la mise à jour du pseudo",
  "searchPlaceholder": "Rechercher un utilisateur...",
  "searchButton": "Rechercher",
  "logout": "Déconnexion",
  "login": "Connexion",
  "register": "Inscription",
  "log_in": "Se connecter",
  "play_to": "Jouer jusqu'à :",
  "apply": "Appliquer",
  "start_game": "Démarrer le jeu",
  "play_again": "Rejouer",
  "game_set": "Paramètres du jeu",
  "player": "Joueur",
  "curr_lim": "Limite actuelle :",
  "win": "gagne !",
  "guest": "invité",
  "dif": "Choisissez la difficulté :",
  "easy": "facile",
  "normal": "normal",
  "hard": "difficile"
}
